README.rst
setup.py
HomeKit_Display_Switch.egg-info/PKG-INFO
HomeKit_Display_Switch.egg-info/SOURCES.txt
HomeKit_Display_Switch.egg-info/dependency_links.txt
HomeKit_Display_Switch.egg-info/entry_points.txt
HomeKit_Display_Switch.egg-info/requires.txt
HomeKit_Display_Switch.egg-info/top_level.txt
display_switch/__init__.py
display_switch/__main__.py
display_switch/display_switch.py
display_switch/load_service.py